scriptengine/__init__.py
scriptengine/context.py
scriptengine/exceptions.py
scriptengine/jinja.py
scriptengine/jobs.py
scriptengine/logging.py
scriptengine/cli/__init__.py
scriptengine/cli/se.py
scriptengine/engines/__init__.py
scriptengine/engines/simple_script_engine.py
scriptengine/helpers/__init__.py
scriptengine/helpers/terminal_colors.py
scriptengine/tasks/__init__.py
scriptengine/tasks/base/__init__.py
scriptengine/tasks/base/chdir.py
scriptengine/tasks/base/command.py
scriptengine/tasks/base/context.py
scriptengine/tasks/base/echo.py
scriptengine/tasks/base/envvars.py
scriptengine/tasks/base/exit.py
scriptengine/tasks/base/find.py
scriptengine/tasks/base/include.py
scriptengine/tasks/base/task_timer.py
scriptengine/tasks/base/template.py
scriptengine/tasks/base/time.py
scriptengine/tasks/base/file/__init__.py
scriptengine/tasks/base/file/copy.py
scriptengine/tasks/base/file/link.py
scriptengine/tasks/base/file/make_dir.py
scriptengine/tasks/base/file/move.py
scriptengine/tasks/base/file/remove.py
scriptengine/tasks/core/__init__.py
scriptengine/tasks/core/loader.py
scriptengine/tasks/core/task.py
scriptengine/tasks/core/timing.py
scriptengine/yaml/__init__.py
scriptengine/yaml/noparse_strings.py
scriptengine/yaml/parser.py
scriptengine-1.2.0.dist-info/LICENSE
scriptengine-1.2.0.dist-info/METADATA
scriptengine-1.2.0.dist-info/WHEEL
scriptengine-1.2.0.dist-info/entry_points.txt
scriptengine-1.2.0.dist-info/top_level.txt
scriptengine-1.2.0.dist-info/RECORD
