Metadata-Version: 2.2
Name: scriptengine
Version: 1.2.0
Summary: A lightweight and extensible framework for executing scripts written in YAML
Author-email: Uwe Fladrich <uwe.fladrich@protonmail.com>
Project-URL: Homepage, https://github.com/uwefladrich/scriptengine
Project-URL: Bug Tracker, https://github.com/uwefladrich/scriptengine/issues
Classifier: Programming Language :: Python :: 3
Classifier: License :: OSI Approved :: GNU General Public License v3 or later (GPLv3+)
Classifier: Operating System :: OS Independent
Requires-Python: >=3.8
License-File: LICENSE
Requires-Dist: python-dateutil
Requires-Dist: deepmerge
Requires-Dist: PyYAML
Requires-Dist: jinja2>=3.0.0
Provides-Extra: tests
Requires-Dist: coverage; extra == "tests"
Requires-Dist: coveralls; extra == "tests"
Requires-Dist: pytest; extra == "tests"
Provides-Extra: docs
Requires-Dist: sphinx; extra == "docs"
Requires-Dist: sphinx-rtd-theme; extra == "docs"
Provides-Extra: all
Requires-Dist: scriptengine[docs,tests]; extra == "all"
